yield_sdk/__init__.py
yield_sdk/api_client.py
yield_sdk/api_result.py
yield_sdk/client.py
yield_sdk/http.py
yield_sdk/version.py
yield_sdk/modules/__init__.py
yield_sdk/modules/customer/__init__.py
yield_sdk/modules/customer/customer_client.py
yield_sdk/modules/customer/customer_payloads.py
yield_sdk/modules/order/__init__.py
yield_sdk/modules/order/order_client.py
yield_sdk/modules/order/order_payloads.py
yield_sdk/modules/self/__init__.py
yield_sdk/modules/self/self_client.py
yield_sdk/modules/self/self_payloads.py
yield_sdk/types/__init__.py
yield_sdk/types/cursor_payload.py
yield_sdk/types/money.py
yield_sdk/types/money_payload.py
yield_sdk/types/page.py
yield_sdk/utils/__init__.py
yield_sdk/utils/import_utils.py
yield_sdk/utils/type_utils.py
yield_sdk-0.7.0.dist-info/METADATA
yield_sdk-0.7.0.dist-info/WHEEL
yield_sdk-0.7.0.dist-info/licenses/LICENSE
yield_sdk-0.7.0.dist-info/RECORD
