Metadata-Version: 2.4
Name: yield-sdk
Version: 0.7.0
Summary: The official Yield SDK for Python
Project-URL: homepage, https://github.com/yield-tech/sdk-python/blob/main/README.md
Project-URL: source, https://github.com/yield-tech/sdk-python
Project-URL: documentation, https://github.com/yield-tech/sdk-python/blob/main/README.md
Author: Yield
License-Expression: Apache-2.0
License-File: LICENSE
Classifier: Development Status :: 4 - Beta
Classifier: Intended Audience :: Developers
Classifier: License :: OSI Approved :: Apache Software License
Classifier: Operating System :: OS Independent
Classifier: Programming Language :: Python
Classifier: Programming Language :: Python :: 3
Classifier: Programming Language :: Python :: 3.10
Classifier: Programming Language :: Python :: 3.11
Classifier: Programming Language :: Python :: 3.12
Classifier: Programming Language :: Python :: 3.13
Classifier: Programming Language :: Python :: Implementation :: CPython
Classifier: Programming Language :: Python :: Implementation :: PyPy
Classifier: Topic :: Software Development :: Libraries :: Python Modules
Requires-Python: >=3.10
Requires-Dist: typing-extensions>=4.13.0
